monacopy/__init__.py
monacopy-0.0.3.dist-info/LICENSE
monacopy-0.0.3.dist-info/METADATA
monacopy-0.0.3.dist-info/WHEEL
monacopy-0.0.3.dist-info/top_level.txt
monacopy-0.0.3.dist-info/RECORD
